conodictor/__init__.py
conodictor/cli.py
conodictor/conodictor.hmm
conodictor/conodictor.pssm
conodictor/conodictor.py
conodictor/conolib.py
conodictor-2.4.1.dist-info/LICENSE
conodictor-2.4.1.dist-info/entry_points.txt
conodictor-2.4.1.dist-info/WHEEL
conodictor-2.4.1.dist-info/METADATA
conodictor-2.4.1.dist-info/RECORD
