Metadata-Version: 2.1
Name: conodictor
Version: 2.4.1
Summary: Prediction and classification of conopeptides
Home-page: https://github.com/koualab/conodictor
License: GPL-3.0-only
Keywords: bioinformatics,classification,prediction,conopeptides
Author: Anicet Ebou
Author-email: anicet.ebou@gmail.com
Maintainer: Anicet Ebou
Maintainer-email: anicet.ebou@gmail.com
Requires-Python: >=3.8,<4.0
Classifier: Development Status :: 5 - Production/Stable
Classifier: Intended Audience :: Developers
Classifier: Intended Audience :: Education
Classifier: Intended Audience :: Science/Research
Classifier: License :: OSI Approved :: GNU General Public License v3 (GPLv3)
Classifier: Natural Language :: English
Classifier: Operating System :: Microsoft :: Windows
Classifier: Operating System :: POSIX :: Linux
Classifier: Operating System :: Unix
Classifier: Programming Language :: Python :: 3
Classifier: Programming Language :: Python :: 3.8
Classifier: Programming Language :: Python :: 3.9
Classifier: Programming Language :: Python :: 3.10
Classifier: Programming Language :: Python :: 3.11
Classifier: Programming Language :: Python :: 3.8
Classifier: Programming Language :: Python :: 3.9
Classifier: Topic :: Scientific/Engineering :: Bio-Informatics
Requires-Dist: bio (>=1.3.3,<2.0.0)
Requires-Dist: matplotlib (>=3.5.1,<4.0.0)
Requires-Dist: pandas (>=1.3.5,<2.0.0)
Requires-Dist: pyfastx (>=0.8.4,<0.9.0)
Requires-Dist: pyhmmer (>=0.10.13,<0.11.0)
Requires-Dist: xphyle (>=4.4.4,<5.0.0)
Project-URL: Documentation, https://github.com/koualab/conodictor
Project-URL: Repository, https://github.com/koualab/conodictor
